rtl/user_domain/xorshift.sv
`timescale 1ns/1ps

module xorshift #(
    parameter int unsigned WIDTH = 32,
    parameter int unsigned SEED  = 32'hDEADBEEF // Default seed
) (
    input  logic        clk_i,
    input  logic        rst_ni, // Using active low reset
    input  logic        en_i,   // Enable for one cycle to generate next number
    output logic [WIDTH-1:0] rand_o
);
    logic [WIDTH-1:0] state_q, state_d;

    // Xorshift+ variant shifts (common for 32-bit)
    localparam int SHIFT_A = 13;
    localparam int SHIFT_B = 17;
    localparam int SHIFT_C = 5;

    // Combinational logic for next state calculation
    // state_d = state_q; // Default assignment
    // state_d = state_d ^ (state_d << SHIFT_A);
    // state_d = state_d ^ (state_d >> SHIFT_B);
    // state_d = state_d ^ (state_d << SHIFT_C);
    // More compact way to write the Xorshift+ variant:
    logic [WIDTH-1:0] t1, t2;
    assign t1 = state_q ^ (state_q << SHIFT_A);
    assign t2 = t1 ^ (t1 >> SHIFT_B);
    assign state_d = t2 ^ (t2 << SHIFT_C);


    // Output the current state
    assign rand_o = state_q;

    // Sequential logic for state update
    always_ff @(posedge clk_i or negedge rst_ni) begin
        if (!rst_ni) begin
            state_q <= SEED; // Initialize state on reset
        end else if (en_i) begin
            state_q <= state_d; // Update state only when enabled
        end
        // Else: state_q holds its value if not enabled
    end
endmodule : xorshift

rtl/user_domain/tb_xorshift.sv
`timescale 1ns/1ps

module tb_xorshift;

  // Parameters
  localparam CLK_PERIOD     = 10ns; // 100 MHz clock
  localparam RESET_DURATION = 2 * CLK_PERIOD;
  localparam int unsigned PRNG_WIDTH = 32;
  localparam int unsigned PRNG_SEED  = 32'hDEADBEEF; // Match DUT default or override

  // Signals
  logic        clk_i;
  logic        rst_ni; // Assuming xorshift uses active low reset
  logic        en_i;
  logic [PRNG_WIDTH-1:0] rand_o;

  // DUT Instantiation
  xorshift #(
    .WIDTH(PRNG_WIDTH),
    .SEED (PRNG_SEED)
  ) dut (
    .clk_i,
    .rst_ni,
    .en_i,
    .rand_o
  );

  // Clock Generation
  initial begin
    clk_i = 1'b0;
    forever #(CLK_PERIOD / 2) clk_i = ~clk_i;
  end

  // Test Scenario
  initial begin
    $dumpfile("tb_xorshift.vcd");
    $dumpvars(0, tb_xorshift);

    // Initialize and Reset
    rst_ni = 1'b0; // Assert reset
    en_i   = 1'b0;
    $display("%t : TB: Asserting Reset", $time);
    #(RESET_DURATION);
    rst_ni = 1'b1; // Deassert reset
    $display("%t : TB: Deasserting Reset. Initial rand_o = 0x%h", $time, rand_o);
    @(posedge clk_i); // Wait for first clock edge after reset

    // Test 1: Enable for one cycle
    $display("--- Test 1: Enable for one cycle ---");
    en_i = 1'b1;
    @(posedge clk_i);
    en_i = 1'b0;
    @(posedge clk_i); // Allow output to settle
    $display("%t : TB: rand_o after 1st enable = 0x%h", $time, rand_o);

    #(5 * CLK_PERIOD);

    // Test 2: Enable for another cycle
    $display("--- Test 2: Enable for another cycle ---");
    en_i = 1'b1;
    @(posedge clk_i);
    en_i = 1'b0;
    @(posedge clk_i);
    $display("%t : TB: rand_o after 2nd enable = 0x%h", $time, rand_o);

    #(5 * CLK_PERIOD);

    // Test 3: Enable for multiple consecutive cycles
    $display("--- Test 3: Enable for 3 consecutive cycles ---");
    en_i = 1'b1;
    @(posedge clk_i);
    $display("%t : TB: rand_o after 3rd enable (cycle 1) = 0x%h", $time, rand_o);
    @(posedge clk_i);
    $display("%t : TB: rand_o after 3rd enable (cycle 2) = 0x%h", $time, rand_o);
    @(posedge clk_i);
    $display("%t : TB: rand_o after 3rd enable (cycle 3) = 0x%h", $time, rand_o);
    en_i = 1'b0;
    @(posedge clk_i);

    #(10 * CLK_PERIOD);
    $display("%t : TB: Test Sequence for xorshift Complete.", $time);
    $finish;
  end

endmodule

tb_xorshift.vcd
$version Generated by VerilatedVcd $end
$timescale 1ps $end
 $scope module $rootio $end
 $upscope $end
 $scope module tb_xorshift $end
  $var real 64 * CLK_PERIOD $end
  $var real 64 , RESET_DURATION $end
  $var wire 32 . PRNG_WIDTH [31:0] $end
  $var wire 32 / PRNG_SEED [31:0] $end
  $var wire 1 ' clk_i $end
  $var wire 1 ( rst_ni $end
  $var wire 1 ) en_i $end
  $var wire 32 # rand_o [31:0] $end
  $scope module dut $end
   $var wire 32 . WIDTH [31:0] $end
   $var wire 32 / SEED [31:0] $end
   $var wire 1 ' clk_i $end
   $var wire 1 ( rst_ni $end
   $var wire 1 ) en_i $end
   $var wire 32 # rand_o [31:0] $end
   $var wire 32 # state_q [31:0] $end
   $var wire 32 $ state_d [31:0] $end
   $var wire 32 0 SHIFT_A [31:0] $end
   $var wire 32 1 SHIFT_B [31:0] $end
   $var wire 32 2 SHIFT_C [31:0] $end
   $var wire 32 % t1 [31:0] $end
   $var wire 32 & t2 [31:0] $end
  $upscope $end
 $upscope $end
$enddefinitions $end


#0
b00000000000000000000000000000000 #
b00000000000000000000000000000000 $
b00000000000000000000000000000000 %
b00000000000000000000000000000000 &
0'
0(
0)
r10 *
r20 ,
b00000000000000000000000000100000 .
b11011110101011011011111011101111 /
b00000000000000000000000000001101 0
b00000000000000000000000000010001 1
b00000000000000000000000000000101 2
#5000
b11011110101011011011111011101111 #
b01000111011111010010000010110111 $
b01101001011100000101111011101111 %
b01101001011100000110101001010111 &
1'
#10000
0'
#15000
1'
#20000
0'
1(
#25000
b01000111011111010010000010110111 #
b10001110000111011001000101000010 $
b11100011011010111100000010110111 %
b11100011011010111011000100000010 &
1'
1)
#30000
0'
#35000
1'
0)
#40000
0'
#45000
1'
#50000
0'
#55000
1'
#60000
0'
#65000
1'
#70000
0'
#75000
1'
#80000
0'
#85000
1'
#90000
0'
#95000
b10001110000111011001000101000010 #
b10111010100011000010010001011000 $
b00111100001101011101000101000010 %
b00111100001101011100111101011000 &
1'
1)
#100000
0'
#105000
1'
0)
#110000
0'
#115000
1'
#120000
0'
#125000
1'
#130000
0'
#135000
1'
#140000
0'
#145000
1'
#150000
0'
#155000
1'
#160000
0'
#165000
b10111010100011000010010001011000 #
b11111110111000000101000000111011 $
b00111110000001110010010001011000 %
b00111110000001110011101101011011 &
1'
1)
#170000
0'
#175000
b11111110111000000101000000111011 #
b01101000000011100000001101001000 $
b11110100111001110011000000111011 %
b11110100111001110100101001001000 &
1'
#180000
0'
#185000
b01101000000011100000001101001000 #
b10100100100011011011100000011011 $
b10101000011001110000001101001000 %
b10101000011001110101011101111011 &
1'
#190000
0'
#195000
1'
0)
